mlflow_xet_plugin/__init__.py
mlflow_xet_plugin/app.py
mlflow_xet_plugin/file_store.py
mlflow_xet_plugin/run_context_provider.py
mlflow_xet_plugin/xet_artifact.py
mlflow_xethub-0.0.0.dist-info/METADATA
mlflow_xethub-0.0.0.dist-info/WHEEL
mlflow_xethub-0.0.0.dist-info/entry_points.txt
mlflow_xethub-0.0.0.dist-info/top_level.txt
mlflow_xethub-0.0.0.dist-info/RECORD
