Metadata-Version: 2.1
Name: mlflow-xethub
Version: 0.0.0
Summary: mlflow[xethub] is a mlflow plugin integrating XetHub with MLflow so that you can use existing MLflow code to track experiments but store artifacts to XetHub.
Home-page: https://github.com/xetdata/Xet-MLflow
Author: XetHub
Author-email: contact@xethub.com
Maintainer: Kelton Zhang
Maintainer-email: kelton@xethub.com
License: BSD-3-Clause
Keywords: ai,collaboration,data-science,developer-tools,git,mlflow,machine-learning,reproducibility
Classifier: Development Status :: 3 - Alpha
Classifier: Programming Language :: Python :: Implementation :: CPython
Classifier: Programming Language :: Python :: Implementation :: PyPy
Classifier: Programming Language :: Python
Classifier: Programming Language :: Python :: 3
Classifier: Programming Language :: Python :: 3 :: Only
Classifier: Programming Language :: Python :: 3.7
Classifier: Programming Language :: Python :: 3.8
Classifier: Programming Language :: Python :: 3.9
Classifier: Programming Language :: Python :: 3.10
Classifier: Programming Language :: Python :: 3.11
Classifier: Operating System :: POSIX :: Linux
Classifier: Operating System :: MacOS
Requires-Python: >=3.7
Requires-Dist: mlflow >=1.27.0
Requires-Dist: pyxet >=0.1.0
